{"sound/soc/qcom/lpass-platform.c": [{"patch_file_name": "sound/soc/qcom/lpass-platform.c", "func_decl_name": "lpass_platform_pcmops_open", "is_cond": false, "line_numbers": [68, 80], "line_cids": ["", ""], "line_strs": ["\tint ret, dma_ch, dir = substream->stream;", "\tif (dma_ch < 0)"]}, {"patch_file_name": "sound/soc/qcom/lpass-platform.c", "func_decl_name": "lpass_platform_pcmops_open", "is_cond": false, "line_numbers": [68, 80], "line_cids": ["", ""], "line_strs": ["\tint ret, dma_ch, dir = substream->stream;", "\tif (dma_ch < 0)"]}]}