{"arch/x86/kernel/cpu/sgx/virt.c": [{"patch_file_name": "arch/x86/kernel/cpu/sgx/virt.c", "func_decl_name": "sgx_vepc_release", "is_cond": false, "line_numbers": [187, 215], "line_cids": ["", ""], "line_strs": ["\t\txa_erase(&vepc->page_array, index);", "\tkfree(vepc);"]}, {"patch_file_name": "arch/x86/kernel/cpu/sgx/virt.c", "func_decl_name": "sgx_vepc_release", "is_cond": false, "line_numbers": [187, 215], "line_cids": ["", ""], "line_strs": ["\t\txa_erase(&vepc->page_array, index);", "\tkfree(vepc);"]}, {"patch_file_name": "arch/x86/kernel/cpu/sgx/virt.c", "func_decl_name": "sgx_vepc_release", "is_cond": false, "line_numbers": [215], "line_cids": [""], "line_strs": ["\tkfree(vepc);"]}, {"patch_file_name": "arch/x86/kernel/cpu/sgx/virt.c", "func_decl_name": "sgx_vepc_release", "is_cond": false, "line_numbers": [215], "line_cids": [""], "line_strs": ["\tkfree(vepc);"]}, {"patch_file_name": "arch/x86/kernel/cpu/sgx/virt.c", "func_decl_name": "sgx_vepc_release", "is_cond": false, "line_numbers": [215], "line_cids": [""], "line_strs": ["\tkfree(vepc);"]}]}