{"drivers/spi/spi.c": [{"patch_file_name": "drivers/spi/spi.c", "func_decl_name": "spi_register_controller", "is_cond": false, "line_numbers": [2279, 2293], "line_cids": ["", ""], "line_strs": ["\t\t\tstatus = spi_get_gpio_descs(ctlr);", "\tif (ctlr->num_chipselect == 0)"]}, {"patch_file_name": "drivers/spi/spi.c", "func_decl_name": "spi_register_controller", "is_cond": false, "line_numbers": [2279, 2293], "line_cids": ["", ""], "line_strs": ["\t\t\tstatus = spi_get_gpio_descs(ctlr);", "\tif (ctlr->num_chipselect == 0)"]}, {"patch_file_name": "drivers/spi/spi.c", "func_decl_name": "spi_register_controller", "is_cond": false, "line_numbers": [2279, 2293], "line_cids": ["", ""], "line_strs": ["\t\t\tstatus = spi_get_gpio_descs(ctlr);", "\tif (ctlr->num_chipselect == 0)"]}, {"patch_file_name": "drivers/spi/spi.c", "func_decl_name": "spi_register_controller", "is_cond": false, "line_numbers": [2302, 2302], "line_cids": ["", ""], "line_strs": ["\t\t\treturn id == -ENOSPC ? -EBUSY : id;", "\t\t\treturn id == -ENOSPC ? -EBUSY : id;"]}, {"patch_file_name": "drivers/spi/spi.c", "func_decl_name": "spi_register_controller", "is_cond": false, "line_numbers": [2279, 2293], "line_cids": ["", ""], "line_strs": ["\t\t\tstatus = spi_get_gpio_descs(ctlr);", "\tif (ctlr->num_chipselect == 0)"]}, {"patch_file_name": "drivers/spi/spi.c", "func_decl_name": "spi_register_controller", "is_cond": false, "line_numbers": [2279, 2293], "line_cids": ["", ""], "line_strs": ["\t\t\tstatus = spi_get_gpio_descs(ctlr);", "\tif (ctlr->num_chipselect == 0)"]}, {"patch_file_name": "drivers/spi/spi.c", "func_decl_name": "spi_register_controller", "is_cond": false, "line_numbers": [2279, 2293], "line_cids": ["", ""], "line_strs": ["\t\t\tstatus = spi_get_gpio_descs(ctlr);", "\tif (ctlr->num_chipselect == 0)"]}]}