{"drivers/tty/n_gsm.c": [{"patch_file_name": "drivers/tty/n_gsm.c", "func_decl_name": "gsm_cleanup_mux", "is_cond": false, "line_numbers": [2153, 2155], "line_cids": ["", ""], "line_strs": ["\tmutex_unlock(&gsm->mutex);", "\tlist_for_each_entry_safe(txq, ntxq, &gsm->tx_list, list)"]}, {"patch_file_name": "drivers/tty/n_gsm.c", "func_decl_name": "gsm_cleanup_mux", "is_cond": false, "line_numbers": [2153, 2155], "line_cids": ["", ""], "line_strs": ["\tmutex_unlock(&gsm->mutex);", "\tlist_for_each_entry_safe(txq, ntxq, &gsm->tx_list, list)"]}]}