{"drivers/gpu/drm/stm/ltdc.c": [{"patch_file_name": "drivers/gpu/drm/stm/ltdc.c", "func_decl_name": "ltdc_crtc_mode_fixup", "is_cond": false, "line_numbers": [507, 510], "line_cids": ["", ""], "line_strs": ["\tstruct ltdc_device *ldev = crtc_to_ltdc(crtc);", "\tif (clk_set_rate(ldev->pixel_clk, rate) < 0) {"]}, {"patch_file_name": "drivers/gpu/drm/stm/ltdc.c", "func_decl_name": "ltdc_crtc_mode_fixup", "is_cond": false, "line_numbers": [507, 510], "line_cids": ["", ""], "line_strs": ["\tstruct ltdc_device *ldev = crtc_to_ltdc(crtc);", "\tif (clk_set_rate(ldev->pixel_clk, rate) < 0) {"]}]}