{"mm/z3fold.c": [{"patch_file_name": "mm/z3fold.c", "func_decl_name": "z3fold_reclaim_page", "is_cond": false, "line_numbers": [668, 670], "line_cids": ["", ""], "line_strs": ["\t\t\tspin_lock(&pool->lock);", "\t\t\t\tatomic64_dec(&pool->pages_nr);"]}, {"patch_file_name": "mm/z3fold.c", "func_decl_name": "z3fold_reclaim_page", "is_cond": false, "line_numbers": [665], "line_cids": [""], "line_strs": ["\t\t\t\tspin_unlock(&pool->lock);"]}, {"patch_file_name": "mm/z3fold.c", "func_decl_name": "z3fold_reclaim_page", "is_cond": false, "line_numbers": [668, 670], "line_cids": ["", ""], "line_strs": ["\t\t\tspin_lock(&pool->lock);", "\t\t\t\tatomic64_dec(&pool->pages_nr);"]}, {"patch_file_name": "mm/z3fold.c", "func_decl_name": "z3fold_reclaim_page", "is_cond": false, "line_numbers": [665], "line_cids": [""], "line_strs": ["\t\t\t\tspin_unlock(&pool->lock);"]}, {"patch_file_name": "mm/z3fold.c", "func_decl_name": "z3fold_reclaim_page", "is_cond": false, "line_numbers": [668, 670], "line_cids": ["", ""], "line_strs": ["\t\t\tspin_lock(&pool->lock);", "\t\t\t\tatomic64_dec(&pool->pages_nr);"]}, {"patch_file_name": "mm/z3fold.c", "func_decl_name": "z3fold_reclaim_page", "is_cond": false, "line_numbers": [668, 670], "line_cids": ["", ""], "line_strs": ["\t\t\tspin_lock(&pool->lock);", "\t\t\t\tatomic64_dec(&pool->pages_nr);"]}, {"patch_file_name": "mm/z3fold.c", "func_decl_name": "z3fold_reclaim_page", "is_cond": false, "line_numbers": [668, 670], "line_cids": ["", ""], "line_strs": ["\t\t\tspin_lock(&pool->lock);", "\t\t\t\tatomic64_dec(&pool->pages_nr);"]}]}