{"drivers/of/of_mdio.c": [{"patch_file_name": "drivers/of/of_mdio.c", "func_decl_name": "of_phy_connect", "is_cond": false, "line_numbers": [224, 227], "line_cids": ["", ""], "line_strs": ["\tif (!phy)", "\treturn phy_connect_direct(dev, phy, hndlr, iface) ? NULL : phy;"]}, {"patch_file_name": "drivers/of/of_mdio.c", "func_decl_name": "of_phy_connect", "is_cond": false, "line_numbers": [224, 227], "line_cids": ["", ""], "line_strs": ["\tif (!phy)", "\treturn phy_connect_direct(dev, phy, hndlr, iface) ? NULL : phy;"]}, {"patch_file_name": "drivers/of/of_mdio.c", "func_decl_name": "of_phy_connect", "is_cond": false, "line_numbers": [227, 227], "line_cids": ["", ""], "line_strs": ["\treturn phy_connect_direct(dev, phy, hndlr, iface) ? NULL : phy;", "\treturn phy_connect_direct(dev, phy, hndlr, iface) ? NULL : phy;"]}, {"patch_file_name": "drivers/of/of_mdio.c", "func_decl_name": "of_phy_connect", "is_cond": false, "line_numbers": [227, 227], "line_cids": ["", ""], "line_strs": ["\treturn phy_connect_direct(dev, phy, hndlr, iface) ? NULL : phy;", "\treturn phy_connect_direct(dev, phy, hndlr, iface) ? NULL : phy;"]}, {"patch_file_name": "drivers/of/of_mdio.c", "func_decl_name": "of_phy_connect", "is_cond": false, "line_numbers": [227, 227], "line_cids": ["", ""], "line_strs": ["\treturn phy_connect_direct(dev, phy, hndlr, iface) ? NULL : phy;", "\treturn phy_connect_direct(dev, phy, hndlr, iface) ? NULL : phy;"]}]}