{"drivers/watchdog/rti_wdt.c": [{"patch_file_name": "drivers/watchdog/rti_wdt.c", "func_decl_name": "rti_wdt_probe", "is_cond": false, "line_numbers": [230, 231], "line_cids": ["", ""], "line_strs": ["\t\tpm_runtime_put_noidle(dev);", "\t\treturn dev_err_probe(dev, ret, \"runtime pm failed\\n\");"]}, {"patch_file_name": "drivers/watchdog/rti_wdt.c", "func_decl_name": "rti_wdt_probe", "is_cond": false, "line_numbers": [230, 231], "line_cids": ["", ""], "line_strs": ["\t\tpm_runtime_put_noidle(dev);", "\t\treturn dev_err_probe(dev, ret, \"runtime pm failed\\n\");"]}]}