{"drivers/net/wwan/mhi_wwan_mbim.c": [{"patch_file_name": "drivers/net/wwan/mhi_wwan_mbim.c", "func_decl_name": "mhi_mbim_probe", "is_cond": false, "line_numbers": [601, 604], "line_cids": ["", ""], "line_strs": ["\tif (!mbim)", "\tdev_set_drvdata(&mhi_dev->dev, mbim);"]}, {"patch_file_name": "drivers/net/wwan/mhi_wwan_mbim.c", "func_decl_name": "mhi_mbim_probe", "is_cond": false, "line_numbers": [601, 604], "line_cids": ["", ""], "line_strs": ["\tif (!mbim)", "\tdev_set_drvdata(&mhi_dev->dev, mbim);"]}, {"patch_file_name": "drivers/net/wwan/mhi_wwan_mbim.c", "func_decl_name": "mhi_mbim_probe", "is_cond": false, "line_numbers": [601, 604], "line_cids": ["", ""], "line_strs": ["\tif (!mbim)", "\tdev_set_drvdata(&mhi_dev->dev, mbim);"]}]}