{"drivers/gpu/drm/vc4/vc4_plane.c": [{"patch_file_name": "drivers/gpu/drm/vc4/vc4_plane.c", "func_decl_name": "vc4_plane_setup_clipping_and_scaling", "is_cond": false, "line_numbers": [297, 325], "line_cids": ["", ""], "line_strs": ["\tvc4_state->y_scaling[0] = vc4_get_scaling_mode(vc4_state->src_h[0],", "\tvc4_state->is_unity = (vc4_state->x_scaling[0] == VC4_SCALING_NONE &&"]}, {"patch_file_name": "drivers/gpu/drm/vc4/vc4_plane.c", "func_decl_name": "vc4_plane_setup_clipping_and_scaling", "is_cond": false, "line_numbers": [297, 325], "line_cids": ["", ""], "line_strs": ["\tvc4_state->y_scaling[0] = vc4_get_scaling_mode(vc4_state->src_h[0],", "\tvc4_state->is_unity = (vc4_state->x_scaling[0] == VC4_SCALING_NONE &&"]}, {"patch_file_name": "drivers/gpu/drm/vc4/vc4_plane.c", "func_decl_name": "vc4_plane_setup_clipping_and_scaling", "is_cond": false, "line_numbers": [297, 325], "line_cids": ["", ""], "line_strs": ["\tvc4_state->y_scaling[0] = vc4_get_scaling_mode(vc4_state->src_h[0],", "\tvc4_state->is_unity = (vc4_state->x_scaling[0] == VC4_SCALING_NONE &&"]}, {"patch_file_name": "drivers/gpu/drm/vc4/vc4_plane.c", "func_decl_name": "vc4_plane_setup_clipping_and_scaling", "is_cond": false, "line_numbers": [297, 325], "line_cids": ["", ""], "line_strs": ["\tvc4_state->y_scaling[0] = vc4_get_scaling_mode(vc4_state->src_h[0],", "\tvc4_state->is_unity = (vc4_state->x_scaling[0] == VC4_SCALING_NONE &&"]}, {"patch_file_name": "drivers/gpu/drm/vc4/vc4_plane.c", "func_decl_name": "vc4_plane_setup_clipping_and_scaling", "is_cond": false, "line_numbers": [297, 325], "line_cids": ["", ""], "line_strs": ["\tvc4_state->y_scaling[0] = vc4_get_scaling_mode(vc4_state->src_h[0],", "\tvc4_state->is_unity = (vc4_state->x_scaling[0] == VC4_SCALING_NONE &&"]}]}