{"drivers/infiniband/hw/ocrdma/ocrdma_verbs.c": [{"patch_file_name": "drivers/infiniband/hw/ocrdma/ocrdma_verbs.c", "func_decl_name": "ocrdma_create_srq", "is_cond": false, "line_numbers": [1901, 1921], "line_cids": ["", ""], "line_strs": ["\tif (status)", "\t\tstatus = ocrdma_mbx_modify_srq(srq, &init_attr->attr);"]}, {"patch_file_name": "drivers/infiniband/hw/ocrdma/ocrdma_verbs.c", "func_decl_name": "ocrdma_create_srq", "is_cond": false, "line_numbers": [1901, 1901], "line_cids": ["", ""], "line_strs": ["\tif (status)", "\tif (status)"]}, {"patch_file_name": "drivers/infiniband/hw/ocrdma/ocrdma_verbs.c", "func_decl_name": "ocrdma_create_srq", "is_cond": false, "line_numbers": [1901, 1901], "line_cids": ["", ""], "line_strs": ["\tif (status)", "\tif (status)"]}]}