{"drivers/scsi/hpsa.c": [{"patch_file_name": "drivers/scsi/hpsa.c", "func_decl_name": "hpsa_update_device_info", "is_cond": false, "line_numbers": [3886, 3910], "line_cids": ["", ""], "line_strs": ["\t\t\thpsa_get_ioaccel_status(h, scsi3addr, this_device);", "\t\t*is_OBDR_device = (this_device->devtype == TYPE_ROM &&"]}, {"patch_file_name": "drivers/scsi/hpsa.c", "func_decl_name": "hpsa_update_device_info", "is_cond": false, "line_numbers": [3887, 3888], "line_cids": ["", ""], "line_strs": ["\t\tvolume_offline = hpsa_volume_offline(h, scsi3addr);", "\t\tif (volume_offline == HPSA_LV_FAILED) {"]}, {"patch_file_name": "drivers/scsi/hpsa.c", "func_decl_name": "hpsa_update_device_info", "is_cond": false, "line_numbers": [3886, 3910], "line_cids": ["", ""], "line_strs": ["\t\t\thpsa_get_ioaccel_status(h, scsi3addr, this_device);", "\t\t*is_OBDR_device = (this_device->devtype == TYPE_ROM &&"]}, {"patch_file_name": "drivers/scsi/hpsa.c", "func_decl_name": "hpsa_update_device_info", "is_cond": false, "line_numbers": [3887, 3888], "line_cids": ["", ""], "line_strs": ["\t\tvolume_offline = hpsa_volume_offline(h, scsi3addr);", "\t\tif (volume_offline == HPSA_LV_FAILED) {"]}, {"patch_file_name": "drivers/scsi/hpsa.c", "func_decl_name": "hpsa_update_device_info", "is_cond": false, "line_numbers": [3884, 3886], "line_cids": ["", ""], "line_strs": ["\t\thpsa_get_raid_level(h, scsi3addr, &this_device->raid_level);", "\t\t\thpsa_get_ioaccel_status(h, scsi3addr, this_device);"]}, {"patch_file_name": "drivers/scsi/hpsa.c", "func_decl_name": "hpsa_update_device_info", "is_cond": false, "line_numbers": [3887, 3888], "line_cids": ["", ""], "line_strs": ["\t\tvolume_offline = hpsa_volume_offline(h, scsi3addr);", "\t\tif (volume_offline == HPSA_LV_FAILED) {"]}, {"patch_file_name": "drivers/scsi/hpsa.c", "func_decl_name": "hpsa_update_device_info", "is_cond": false, "line_numbers": [3886, 3910], "line_cids": ["", ""], "line_strs": ["\t\t\thpsa_get_ioaccel_status(h, scsi3addr, this_device);", "\t\t*is_OBDR_device = (this_device->devtype == TYPE_ROM &&"]}, {"patch_file_name": "drivers/scsi/hpsa.c", "func_decl_name": "hpsa_update_device_info", "is_cond": false, "line_numbers": [3887, 3888], "line_cids": ["", ""], "line_strs": ["\t\tvolume_offline = hpsa_volume_offline(h, scsi3addr);", "\t\tif (volume_offline == HPSA_LV_FAILED) {"]}, {"patch_file_name": "drivers/scsi/hpsa.c", "func_decl_name": "hpsa_update_device_info", "is_cond": false, "line_numbers": [3886, 3910], "line_cids": ["", ""], "line_strs": ["\t\t\thpsa_get_ioaccel_status(h, scsi3addr, this_device);", "\t\t*is_OBDR_device = (this_device->devtype == TYPE_ROM &&"]}, {"patch_file_name": "drivers/scsi/hpsa.c", "func_decl_name": "hpsa_update_device_info", "is_cond": false, "line_numbers": [3887, 3888], "line_cids": ["", ""], "line_strs": ["\t\tvolume_offline = hpsa_volume_offline(h, scsi3addr);", "\t\tif (volume_offline == HPSA_LV_FAILED) {"]}, {"patch_file_name": "drivers/scsi/hpsa.c", "func_decl_name": "hpsa_update_device_info", "is_cond": false, "line_numbers": [3884, 3886], "line_cids": ["", ""], "line_strs": ["\t\thpsa_get_raid_level(h, scsi3addr, &this_device->raid_level);", "\t\t\thpsa_get_ioaccel_status(h, scsi3addr, this_device);"]}, {"patch_file_name": "drivers/scsi/hpsa.c", "func_decl_name": "hpsa_update_device_info", "is_cond": false, "line_numbers": [3887, 3888], "line_cids": ["", ""], "line_strs": ["\t\tvolume_offline = hpsa_volume_offline(h, scsi3addr);", "\t\tif (volume_offline == HPSA_LV_FAILED) {"]}, {"patch_file_name": "drivers/scsi/hpsa.c", "func_decl_name": "hpsa_update_device_info", "is_cond": false, "line_numbers": [3887, 3888], "line_cids": ["", ""], "line_strs": ["\t\tvolume_offline = hpsa_volume_offline(h, scsi3addr);", "\t\tif (volume_offline == HPSA_LV_FAILED) {"]}, {"patch_file_name": "drivers/scsi/hpsa.c", "func_decl_name": "hpsa_update_device_info", "is_cond": false, "line_numbers": [3886, 3910], "line_cids": ["", ""], "line_strs": ["\t\t\thpsa_get_ioaccel_status(h, scsi3addr, this_device);", "\t\t*is_OBDR_device = (this_device->devtype == TYPE_ROM &&"]}, {"patch_file_name": "drivers/scsi/hpsa.c", "func_decl_name": "hpsa_update_device_info", "is_cond": false, "line_numbers": [3886, 3910], "line_cids": ["", ""], "line_strs": ["\t\t\thpsa_get_ioaccel_status(h, scsi3addr, this_device);", "\t\t*is_OBDR_device = (this_device->devtype == TYPE_ROM &&"]}, {"patch_file_name": "drivers/scsi/hpsa.c", "func_decl_name": "hpsa_update_device_info", "is_cond": false, "line_numbers": [3887, 3888], "line_cids": ["", ""], "line_strs": ["\t\tvolume_offline = hpsa_volume_offline(h, scsi3addr);", "\t\tif (volume_offline == HPSA_LV_FAILED) {"]}, {"patch_file_name": "drivers/scsi/hpsa.c", "func_decl_name": "hpsa_update_device_info", "is_cond": false, "line_numbers": [3884, 3886], "line_cids": ["", ""], "line_strs": ["\t\thpsa_get_raid_level(h, scsi3addr, &this_device->raid_level);", "\t\t\thpsa_get_ioaccel_status(h, scsi3addr, this_device);"]}, {"patch_file_name": "drivers/scsi/hpsa.c", "func_decl_name": "hpsa_update_device_info", "is_cond": false, "line_numbers": [3887, 3888], "line_cids": ["", ""], "line_strs": ["\t\tvolume_offline = hpsa_volume_offline(h, scsi3addr);", "\t\tif (volume_offline == HPSA_LV_FAILED) {"]}, {"patch_file_name": "drivers/scsi/hpsa.c", "func_decl_name": "hpsa_update_device_info", "is_cond": false, "line_numbers": [3887, 3888], "line_cids": ["", ""], "line_strs": ["\t\tvolume_offline = hpsa_volume_offline(h, scsi3addr);", "\t\tif (volume_offline == HPSA_LV_FAILED) {"]}, {"patch_file_name": "drivers/scsi/hpsa.c", "func_decl_name": "hpsa_update_device_info", "is_cond": false, "line_numbers": [3884, 3910], "line_cids": ["", ""], "line_strs": ["\t\thpsa_get_raid_level(h, scsi3addr, &this_device->raid_level);", "\t\t*is_OBDR_device = (this_device->devtype == TYPE_ROM &&"]}]}