{"kernel/bpf/syscall.c": [{"patch_file_name": "kernel/bpf/syscall.c", "func_decl_name": "fixup_bpf_calls", "is_cond": false, "line_numbers": [603, 625], "line_cids": ["", ""], "line_strs": ["\tfor (i = 0; i < prog->len; i++) {", "\t\t\t\tprog->cb_access = 1;"]}, {"patch_file_name": "kernel/bpf/syscall.c", "func_decl_name": "fixup_bpf_calls", "is_cond": false, "line_numbers": [603, 625], "line_cids": ["", ""], "line_strs": ["\tfor (i = 0; i < prog->len; i++) {", "\t\t\t\tprog->cb_access = 1;"]}, {"patch_file_name": "kernel/bpf/syscall.c", "func_decl_name": "fixup_bpf_calls", "is_cond": false, "line_numbers": [603, 625], "line_cids": ["", ""], "line_strs": ["\tfor (i = 0; i < prog->len; i++) {", "\t\t\t\tprog->cb_access = 1;"]}, {"patch_file_name": "kernel/bpf/syscall.c", "func_decl_name": "fixup_bpf_calls", "is_cond": false, "line_numbers": [603, 625], "line_cids": ["", ""], "line_strs": ["\tfor (i = 0; i < prog->len; i++) {", "\t\t\t\tprog->cb_access = 1;"]}, {"patch_file_name": "kernel/bpf/syscall.c", "func_decl_name": "fixup_bpf_calls", "is_cond": false, "line_numbers": [603, 625], "line_cids": ["", ""], "line_strs": ["\tfor (i = 0; i < prog->len; i++) {", "\t\t\t\tprog->cb_access = 1;"]}, {"patch_file_name": "kernel/bpf/syscall.c", "func_decl_name": "fixup_bpf_calls", "is_cond": false, "line_numbers": [603, 625], "line_cids": ["", ""], "line_strs": ["\tfor (i = 0; i < prog->len; i++) {", "\t\t\t\tprog->cb_access = 1;"]}, {"patch_file_name": "kernel/bpf/syscall.c", "func_decl_name": "fixup_bpf_calls", "is_cond": false, "line_numbers": [603, 625], "line_cids": ["", ""], "line_strs": ["\tfor (i = 0; i < prog->len; i++) {", "\t\t\t\tprog->cb_access = 1;"]}, {"patch_file_name": "kernel/bpf/syscall.c", "func_decl_name": "fixup_bpf_calls", "is_cond": false, "line_numbers": [603, 625], "line_cids": ["", ""], "line_strs": ["\tfor (i = 0; i < prog->len; i++) {", "\t\t\t\tprog->cb_access = 1;"]}, {"patch_file_name": "kernel/bpf/syscall.c", "func_decl_name": "fixup_bpf_calls", "is_cond": false, "line_numbers": [603, 625], "line_cids": ["", ""], "line_strs": ["\tfor (i = 0; i < prog->len; i++) {", "\t\t\t\tprog->cb_access = 1;"]}, {"patch_file_name": "kernel/bpf/syscall.c", "func_decl_name": "fixup_bpf_calls", "is_cond": false, "line_numbers": [603, 625], "line_cids": ["", ""], "line_strs": ["\tfor (i = 0; i < prog->len; i++) {", "\t\t\t\tprog->cb_access = 1;"]}]}