{"fs/configfs/dir.c": [{"patch_file_name": "fs/configfs/dir.c", "func_decl_name": "configfs_unregister_subsystem", "is_cond": false, "line_numbers": [1915], "line_cids": [""], "line_strs": ["\tmutex_lock(&configfs_symlink_mutex);"]}, {"patch_file_name": "fs/configfs/dir.c", "func_decl_name": "configfs_unregister_subsystem", "is_cond": false, "line_numbers": [1921], "line_cids": [""], "line_strs": ["\tmutex_unlock(&configfs_symlink_mutex);"]}, {"patch_file_name": "fs/configfs/dir.c", "func_decl_name": "configfs_unregister_subsystem", "is_cond": false, "line_numbers": [1915], "line_cids": [""], "line_strs": ["\tmutex_lock(&configfs_symlink_mutex);"]}, {"patch_file_name": "fs/configfs/dir.c", "func_decl_name": "configfs_unregister_subsystem", "is_cond": false, "line_numbers": [1921], "line_cids": [""], "line_strs": ["\tmutex_unlock(&configfs_symlink_mutex);"]}]}